Metadata-Version: 1.1
Name: F2Depine
Version: 0.0.1
Summary: Para resolver ejercicios de F2
Home-page: https://github.com/Corri3141/F2Depine
Author: Corrado De Luca
Author-email: corrideluca@gmail.com
License: MIT
Keywords: f2depine
Platform: UNKNOWN
Classifier: Development Status :: 5 - Production/Stable
Classifier: Intended Audience :: Education
Classifier: Operating System :: Microsoft :: Windows :: Windows 10
Classifier: License :: OSI Approved :: MIT License
Classifier: Programming Language :: Python :: 3
